codecpy/__init__.py
codecpy/codecs/__init__.py
codecpy/colors/__init__.py
codecpy/container/__init__.py
codecpy/mime/__init__.py
codecpy/mime/info.py
codecpy/profiles/__init__.py
codecpy-0.1.3.dist-info/LICENSE
codecpy-0.1.3.dist-info/METADATA
codecpy-0.1.3.dist-info/WHEEL
codecpy-0.1.3.dist-info/top_level.txt
codecpy-0.1.3.dist-info/RECORD
