Metadata-Version: 2.1
Name: codecpy
Version: 0.1.3
Summary: A comprehensive Python library for codec identification, normalization and media format analysis
Home-page: https://github.com/ReiDoBrega/codecpy
Author: ReiDoBrega
Author-email: pedro94782079@gmail.com
License: MIT
Project-URL: Homepage, https://github.com/ReiDoBrega/codecpy
Project-URL: Repository, https://github.com/ReiDoBrega/codecpy
Project-URL: Bug Tracker, https://github.com/ReiDoBrega/codecpy/issues
Keywords: codec,media,video,audio,format,container,mime-type,h264,h265,aac,mp4,webm,matroska,mkv,hls,dash
Classifier: Development Status :: 4 - Beta
Classifier: Intended Audience :: Developers
Classifier: Programming Language :: Python :: 3
Classifier: Programming Language :: Python :: 3.7
Classifier: Programming Language :: Python :: 3.8
Classifier: Programming Language :: Python :: 3.9
Classifier: Programming Language :: Python :: 3.10
Classifier: Programming Language :: Python :: 3.11
Classifier: License :: OSI Approved :: MIT License
Classifier: Operating System :: OS Independent
Classifier: Topic :: Software Development :: Libraries :: Python Modules
Classifier: Topic :: Multimedia :: Sound/Audio
Classifier: Topic :: Multimedia :: Video
Classifier: Topic :: Multimedia :: Graphics
Requires-Python: >=3.7
License-File: LICENSE
Requires-Dist: dataclasses>=0.6; python_version < "3.7"
Requires-Dist: typing-extensions>=3.7.4; python_version < "3.8"
